[
  {
    "user_id": "dBEErWGti0Y8Ytfx1W0SlcEZ29H2",
    "task": "Identify one small act of kindness you performed today.",
    "date": "2025-06-30",
    "completed": false,
    "timestamp": "2025-06-30T15:23:39.625582"
  },
  {
    "user_id": "dBEErWGti0Y8Ytfx1W0SlcEZ29H2",
    "task": "List three things you are grateful for right now.",
    "date": "2025-07-01",
    "completed": false,
    "timestamp": "2025-07-01T16:02:20.719718"
  },
  {
    "user_id": "dBEErWGti0Y8Ytfx1W0SlcEZ29H2",
    "task": "Reflect on one small act of kindness you did today.",
    "date": "2025-07-03",
    "completed": true,
    "timestamp": "2025-07-03T17:20:14.292921",
    "completion_timestamp": "2025-07-03T17:20:24.977945"
  },
  {
    "user_id": "dBEErWGti0Y8Ytfx1W0SlcEZ29H2",
    "task": "Reflect on one thing you are grateful for today.",
    "date": "2025-07-04",
    "completed": true,
    "timestamp": "2025-07-04T07:34:10.488357",
    "completion_timestamp": "2025-07-04T17:48:05.072024"
  },
  {
    "user_id": "dBEErWGti0Y8Ytfx1W0SlcEZ29H2",
    "task": "Have you ever acted on impulse just because it felt right in the moment? What happened?",
    "date": "2025-07-05",
    "completed": false,
    "timestamp": "2025-07-05T11:49:30.225846"
  },
  {
    "user_id": "qlKzXtQ28EOeU6qa1D0LtPpcOLT2",
    "task": "Have you ever acted on impulse just because it felt right in the moment? What happened?",
    "date": "2025-07-05",
    "completed": false,
    "timestamp": "2025-07-05T12:09:55.673172"
  },
  {
    "user_id": "dBEErWGti0Y8Ytfx1W0SlcEZ29H2",
    "task": "Do you ever switch perspectives just to understand something more deeply?",
    "date": "2025-07-06",
    "completed": true,
    "timestamp": "2025-07-06T12:21:31.923813",
    "completion_timestamp": "2025-07-06T12:21:41.512120"
  },
  {
    "user_id": "dBEErWGti0Y8Ytfx1W0SlcEZ29H2",
    "task": "When do you feel most authentic \u2014 when leading, listening, creating, or something else?",
    "date": "2025-07-07",
    "completed": false,
    "timestamp": "2025-07-07T07:34:42.751130"
  },
  {
    "user_id": "dBEErWGti0Y8Ytfx1W0SlcEZ29H2",
    "task": "If everyone followed your philosophy of life, what kind of world would we have?",
    "date": "2025-07-08",
    "completed": false,
    "timestamp": "2025-07-08T11:15:11.711195"
  },
  {
    "user_id": "dBEErWGti0Y8Ytfx1W0SlcEZ29H2",
    "task": "Have your values changed over the years? What sparked the shift?",
    "date": "2025-07-09",
    "completed": false,
    "timestamp": "2025-07-09T06:34:20.642859"
  },
  {
    "user_id": "H23uQutto0MEwJoRmQeWSOr6m2U2",
    "task": "What's more important to you \u2014 being right, or being helpful in a larger system?",
    "date": "2025-07-09",
    "completed": false,
    "timestamp": "2025-07-09T07:58:02.241244"
  },
  {
    "user_id": "dBEErWGti0Y8Ytfx1W0SlcEZ29H2",
    "task": "Describe a time when you took control of a situation without waiting for permission. Why did you do it?",
    "date": "2025-07-11",
    "completed": false,
    "timestamp": "2025-07-11T12:47:59.703941"
  },
  {
    "user_id": "dBEErWGti0Y8Ytfx1W0SlcEZ29H2",
    "task": "What does growth mean to you?",
    "date": "2025-07-14",
    "completed": false,
    "timestamp": "2025-07-14T13:32:49.962206"
  },
  {
    "user_id": "dBEErWGti0Y8Ytfx1W0SlcEZ29H2",
    "task": "Do you adapt your behavior depending on the environment or people around you?",
    "date": "2025-07-15",
    "completed": false,
    "timestamp": "2025-07-15T09:30:40.921870"
  },
  {
    "user_id": "dBEErWGti0Y8Ytfx1W0SlcEZ29H2",
    "task": "What part of your identity do you feel is constantly evolving?",
    "date": "2025-07-18",
    "completed": false,
    "timestamp": "2025-07-18T11:58:05.850037"
  },
  {
    "user_id": "dBEErWGti0Y8Ytfx1W0SlcEZ29H2",
    "task": "Do you adapt your behavior depending on the environment or people around you?",
    "date": "2025-07-19",
    "completed": false,
    "timestamp": "2025-07-19T16:18:26.142402"
  },
  {
    "user_id": "qlKzXtQ28EOeU6qa1D0LtPpcOLT2",
    "task": "What does growth mean to you?",
    "date": "2025-07-21",
    "completed": false,
    "timestamp": "2025-07-21T08:12:29.180155"
  },
  {
    "user_id": "dBEErWGti0Y8Ytfx1W0SlcEZ29H2",
    "task": "What does growth mean to you?",
    "date": "2025-07-21",
    "completed": false,
    "timestamp": "2025-07-21T08:12:45.723764"
  },
  {
    "user_id": "dBEErWGti0Y8Ytfx1W0SlcEZ29H2",
    "task": "What does growth mean to you?",
    "date": "2025-07-23",
    "completed": false,
    "timestamp": "2025-07-23T07:49:45.458306"
  },
  {
    "user_id": "dBEErWGti0Y8Ytfx1W0SlcEZ29H2",
    "task": "What does growth mean to you?",
    "date": "2025-07-24",
    "completed": false,
    "timestamp": "2025-07-24T09:47:34.842792"
  },
  {
    "user_id": "dBEErWGti0Y8Ytfx1W0SlcEZ29H2",
    "task": "Describe a time you made a decision that honored both logic and intuition.",
    "date": "2025-07-25",
    "completed": false,
    "timestamp": "2025-07-25T06:38:44.477493"
  },
  {
    "user_id": "dBEErWGti0Y8Ytfx1W0SlcEZ29H2",
    "task": "How do you react when someone limits your freedom or questions your ability?",
    "date": "2025-07-26",
    "completed": false,
    "timestamp": "2025-07-26T10:20:56.911949"
  },
  {
    "user_id": "dBEErWGti0Y8Ytfx1W0SlcEZ29H2",
    "task": "Have you ever felt part of something much larger than yourself? What was that experience like?",
    "date": "2025-07-27",
    "completed": false,
    "timestamp": "2025-07-27T12:09:58.370565"
  },
  {
    "user_id": "dBEErWGti0Y8Ytfx1W0SlcEZ29H2",
    "task": "Do you value clarity or complexity more when making sense of life?",
    "date": "2025-07-29",
    "completed": false,
    "timestamp": "2025-07-29T07:15:48.712000"
  },
  {
    "user_id": "dBEErWGti0Y8Ytfx1W0SlcEZ29H2",
    "task": "How do you define harmony \u2014 is it internal, collective, spiritual?",
    "date": "2025-07-30",
    "completed": false,
    "timestamp": "2025-07-30T17:43:53.032423"
  },
  {
    "user_id": "dBEErWGti0Y8Ytfx1W0SlcEZ29H2",
    "task": "Have you ever pushed yourself too hard to prove something to others? Why did it matter so much?",
    "date": "2025-07-31",
    "completed": false,
    "timestamp": "2025-07-31T07:16:24.758588"
  },
  {
    "user_id": "dBEErWGti0Y8Ytfx1W0SlcEZ29H2",
    "task": "Have you ever realized both sides of an argument were valid? How did you respond?",
    "date": "2025-08-01",
    "completed": false,
    "timestamp": "2025-08-01T07:20:27.003750"
  },
  {
    "user_id": "dBEErWGti0Y8Ytfx1W0SlcEZ29H2",
    "task": "Think of a time you followed a rule that you didn't fully agree with. Why did you do it?",
    "date": "2025-08-03",
    "completed": false,
    "timestamp": "2025-08-03T11:58:42.613590"
  },
  {
    "user_id": "dBEErWGti0Y8Ytfx1W0SlcEZ29H2",
    "task": "How do you decide what's worth standing up for?",
    "date": "2025-08-06",
    "completed": false,
    "timestamp": "2025-08-06T11:47:58.453882"
  },
  {
    "user_id": "dBEErWGti0Y8Ytfx1W0SlcEZ29H2",
    "task": "Are there superstitions or rituals you follow without fully knowing why? What do they mean to you?",
    "date": "2025-08-07",
    "completed": false,
    "timestamp": "2025-08-07T18:02:17.481745"
  },
  {
    "user_id": "dBEErWGti0Y8Ytfx1W0SlcEZ29H2",
    "task": "When was the last time you questioned your worldview?",
    "date": "2025-08-09",
    "completed": false,
    "timestamp": "2025-08-09T18:46:06.339448"
  },
  {
    "user_id": "dBEErWGti0Y8Ytfx1W0SlcEZ29H2",
    "task": "How do you decide when to speak up for others versus stay quiet for harmony?",
    "date": "2025-08-10",
    "completed": false,
    "timestamp": "2025-08-10T19:45:01.811766"
  },
  {
    "user_id": "dBEErWGti0Y8Ytfx1W0SlcEZ29H2",
    "task": "How do you deal with people who challenge your authority or choices?",
    "date": "2025-08-11",
    "completed": false,
    "timestamp": "2025-08-11T19:16:22.848205"
  }
]